kina/__init__.py
kina/azure/__init__.py
kina/azure/kubernetes.py
kina/azure/registry.py
kina/azure/resource_groups.py
kina/azure/virtual_networks.py
kina/jobs/__init__.py
kina/jobs/flux.py
kina/kubectl/__init__.py
kina-1.4.4.dist-info/licenses/LICENSE
kina-1.4.4.dist-info/METADATA
kina-1.4.4.dist-info/WHEEL
kina-1.4.4.dist-info/entry_points.txt
kina-1.4.4.dist-info/top_level.txt
kina-1.4.4.dist-info/RECORD
