Metadata-Version: 2.4
Name: kina
Version: 1.4.4
Summary: A simple tool to create ephemeral AKS Clusters
Requires-Python: >=3.13
License-File: LICENSE
Requires-Dist: azure-identity>=1.22.0
Requires-Dist: azure-mgmt-authorization>=4.0.0
Requires-Dist: azure-mgmt-compute>=34.1.0
Requires-Dist: azure-mgmt-containerregistry>=14.0.0
Requires-Dist: azure-mgmt-containerservice>=35.0.0
Requires-Dist: azure-mgmt-network>=28.1.0
Requires-Dist: azure-mgmt-resource>=23.3.0
Requires-Dist: pyyaml>=6.0.2
Requires-Dist: requests>=2.32.3
Requires-Dist: typer>=0.15.3
Dynamic: license-file
